enkeep_ctp/__init__.py
enkeep_ctp/api/__init__.py
enkeep_ctp/api/ctp_constant.py
enkeep_ctp/api/libthostmduserapi_se.so
enkeep_ctp/api/libthosttraderapi_se.so
enkeep_ctp/api/vnctpmd.cpython-313-x86_64-linux-gnu.so
enkeep_ctp/api/vnctptd.cpython-313-x86_64-linux-gnu.so
enkeep_ctp/gateway/__init__.py
enkeep_ctp/gateway/ctp_gateway.py
enkeep_ctp.libs/libthostmduserapi_se-6da3e23a.so
enkeep_ctp.libs/libthosttraderapi_se-54a23168.so
enkeep_ctp-6.7.7.11.dist-info/METADATA
enkeep_ctp-6.7.7.11.dist-info/WHEEL
enkeep_ctp-6.7.7.11.dist-info/RECORD
