Metadata-Version: 2.1
Name: enkeep_ctp
Version: 6.7.7.11
Summary: CTP gateway for enkeep_trade quant trading framework.
Keywords: quant,quantitative,investment,trading,algotrading,ctp
License: MIT
Classifier: Development Status :: 5 - Production/Stable
Classifier: Operating System :: Microsoft :: Windows
Classifier: Operating System :: POSIX :: Linux
Classifier: Operating System :: MacOS
Classifier: Programming Language :: Python :: 3
Classifier: Programming Language :: Python :: 3.10
Classifier: Programming Language :: Python :: 3.11
Classifier: Programming Language :: Python :: 3.12
Classifier: Programming Language :: Python :: 3.13
Classifier: Topic :: Office/Business :: Financial :: Investment
Classifier: Programming Language :: Python :: Implementation :: CPython
Classifier: License :: OSI Approved :: MIT License
Classifier: Natural Language :: Chinese (Simplified)
Project-URL: Homepage, https://www.enkeep.com
Requires-Python: >=3.10
Requires-Dist: pybind11>=2.13.6
